{  
   "Data":[  
      {  
         "Id":1000005683,
         "Name":"#M13050518234259",
         "Description":""
      },
      {  
         "Id":1000006475,
         "Name":"#ngaff",
         "Description":""
      },
      {  
         "Id":1000006476,
         "Name":"#ngaff2",
         "Description":""
      },
      {  
         "Id":1000000331,
         "Name":"#ReportHieu",
         "Description":""
      },
      {  
         "Id":1000002635,
         "Name":"#specialObject",
         "Description":""
      }
   ],
   "NumberOfPages":28,
   "CurrentPage":1,
   "Privilege":5,
   "ExportPriv":0,
   "TemplatePriv":0,
   "BulkPriv":0
}
